Workbook

Sheet Registro de Riesgos
A1: Gestion de Riesgos - Migracion y modernizacion de un Core Bancario
A2: Banco regional | 500,000 clientes activos | Inactividad maxima permitida: 30 minutos | Plazo: 8 meses
A4: ID | B4: Descripcion del problema | C4: Riesgo | D4: Causa raiz | E4: Fecha de identificacion | F4: Tipo de riesgo | G4: Categoria del riesgo | H4: Objetivo del proyecto afectado | I4: Tipo de impacto | J4: Probabilidad | K4: Impacto Alcance | L4: Impacto Tiempo | M4: Impacto Costo | N4: Impacto Calidad | O4: Valoracion global del riesgo | P4: Prioridad | Q4: Dueno (Owner) | R4: Responsable | S4: Plan de respuesta predeterminado | T4: Estrategia de respuesta adoptada | U4: Plan de respuesta adoptado | V4: Riesgo residual / secundario | W4: Riesgo activado? | X4: Fecha de activacion
A5: R1 | B5: Migracion del core en una ventana limitada de corte | C5: Interrupcion del servicio superior a 30 minutos durante el cutover | D5: Planificacion deficiente, scripts no probados y tiempos reales subestimados | E5: 2026-05-09 | F5: Amenaza | G5: Tecnico / Operacional | H5: Continuidad operativa y disponibilidad | I5: Directo | J5: 4 | K5: 4 | L5: 5 | M5: 4 | N5: 5 | O5: =J5*MAX(K5:N5) | P5: =IF(O5>=16,"Critica",IF(O5>=12,"Alta",IF(O5>=6,"Media","Baja"))) | Q5: Lider de Migracion | R5: Operaciones + Infraestructura | S5: Preparar plan detallado de cutover y rollback | T5: Mitigar | U5: Ejecutar simulacros completos, estrategia blue-green, checklist minuto a minuto y ventana de baja demanda | V5: Retraso menor en algunos servicios no criticos | W5: No
A6: R2 | B6: Conversion y traslado de datos bancarios historicos y vigentes | C6: Perdida, corrupcion o inconsistencia de datos | D6: Mapeo incorrecto, ETL defectuoso y conciliacion insuficiente | E6: 2026-05-09 | F6: Amenaza | G6: Datos | H6: Integridad de datos y calidad del servicio | I6: Directo | J6: 3 | K6: 5 | L6: 4 | M6: 4 | N6: 5 | O6: =J6*MAX(K6:N6) | P6: =IF(O6>=16,"Critica",IF(O6>=12,"Alta",IF(O6>=6,"Media","Baja"))) | Q6: Arquitecto de Datos | R6: Equipo de Datos / DBA | S6: Respaldos completos y validacion de integridad | T6: Mitigar | U6: Migracion piloto, conciliacion cuenta a cuenta, doble validacion de saldos y hash de integridad | V6: Diferencias menores en datos no criticos | W6: No
A7: R3 | B7: Adaptacion del sistema a nuevas normas bancarias dentro del plazo | C7: Incumplimiento regulatorio antes de la fecha limite | D7: Interpretacion incompleta de requisitos normativos y retrasos en controles | E7: 2026-05-09 | F7: Amenaza | G7: Regulatorio / Legal | H7: Cumplimiento y plazo | I7: Directo | J7: 3 | K7: 4 | L7: 5 | M7: 4 | N7: 5 | O7: =J7*MAX(K7:N7) | P7: =IF(O7>=16,"Critica",IF(O7>=12,"Alta",IF(O7>=6,"Media","Baja"))) | Q7: Oficial de Cumplimiento | R7: PM + Compliance + Legal | S7: Revisiones normativas periodicas | T7: Evitar / Mitigar | U7: Crear matriz de cumplimiento, validaciones con auditoria, evidencias desde el inicio e hitos regulatorios obligatorios | V7: Observaciones menores del regulador | W7: No
A8: R4 | B8: Nuevo entorno basado en microservicios puede no rendir como se espera | C8: Bajo desempeno del nuevo core en produccion | D8: Arquitectura no optimizada, mala configuracion cloud y latencia entre servicios | E8: 2026-05-09 | F8: Amenaza | G8: Tecnico / Rendimiento | H8: Disponibilidad y experiencia del cliente | I8: Directo | J8: 4 | K8: 4 | L8: 4 | M8: 4 | N8: 5 | O8: =J8*MAX(K8:N8) | P8: =IF(O8>=16,"Critica",IF(O8>=12,"Alta",IF(O8>=6,"Media","Baja"))) | Q8: Arquitecto de Solucion | R8: SRE / DevOps / Arquitectura | S8: Probar rendimiento antes del go-live | T8: Mitigar | U8: Pruebas de carga, estres y picos; ajuste de autoscaling, cache, colas y observabilidad | V8: Degradacion temporal de modulos secundarios | W8: No
A9: R5 | B9: Dependencia de integraciones con ATM, banca movil, pagos y clearing | C9: Fallas en integraciones con sistemas internos y externos | D9: APIs incompletas, contratos mal definidos y dependencias legacy | E9: 2026-05-09 | F9: Amenaza | G9: Integracion | H9: Operacion bancaria de punta a punta | I9: Directo | J9: 4 | K9: 4 | L9: 4 | M9: 3 | N9: 5 | O9: =J9*MAX(K9:N9) | P9: =IF(O9>=16,"Critica",IF(O9>=12,"Alta",IF(O9>=6,"Media","Baja"))) | Q9: Lider de Integraciones | R9: Equipos de Canales / Middleware | S9: Inventario y pruebas de interfaces | T9: Mitigar | U9: Contract testing, pruebas E2E, mocks certificados, transicion por canal y fallback con legado | V9: Fallas parciales en canales de baja transaccionalidad | W9: No
A10: R6 | B10: Nueva infraestructura cloud expuesta a amenazas de seguridad | C10: Vulnerabilidades o brechas de ciberseguridad | D10: Configuracion insegura, exceso de permisos y secretos mal gestionados | E10: 2026-05-09 | F10: Amenaza | G10: Seguridad | H10: Confidencialidad, integridad y cumplimiento | I10: Directo | J10: 3 | K10: 4 | L10: 4 | M10: 5 | N10: 5 | O10: =J10*MAX(K10:N10) | P10: =IF(O10>=16,"Critica",IF(O10>=12,"Alta",IF(O10>=6,"Media","Baja"))) | Q10: CISO | R10: Seguridad + Cloud Team | S10: Aplicar controles de seguridad desde el diseno | T10: Mitigar | U10: IAM de minimo privilegio, cifrado, vault de secretos, SAST/DAST, pentest y monitoreo SIEM | V10: Riesgo residual de amenazas avanzadas persistentes | W10: No
A11: R7 | B11: El alcance tecnico del proyecto puede superar la capacidad del plazo | C11: Retraso del cronograma por complejidad no prevista | D11: Deuda tecnica legacy, dependencias ocultas y estimaciones optimistas | E11: 2026-05-09 | F11: Amenaza | G11: Gestion / Cronograma | H11: Plazo y cumplimiento regulatorio | I11: Directo | J11: 4 | K11: 4 | L11: 5 | M11: 4 | N11: 4 | O11: =J11*MAX(K11:N11) | P11: =IF(O11>=16,"Critica",IF(O11>=12,"Alta",IF(O11>=6,"Media","Baja"))) | Q11: Project Manager | R11: PMO + Arquitectura + Lideres Tecnicos | S11: Seguimiento estricto del camino critico | T11: Mitigar | U11: Replanificar por olas, priorizar funciones regulatorias, buffers tecnicos y revision semanal de hitos | V11: Recorte de funcionalidades no esenciales | W11: No
A12: R8 | B12: El equipo actual puede no dominar cloud y microservicios | C12: Falta de experiencia tecnica del equipo | D12: Conocimiento centrado en sistemas on-premise y monoliticos | E12: 2026-05-09 | F12: Amenaza | G12: Recursos Humanos / Tecnico | H12: Calidad tecnica y cronograma | I12: Indirecto | J12: 3 | K12: 3 | L12: 4 | M12: 3 | N12: 4 | O12: =J12*MAX(K12:N12) | P12: =IF(O12>=16,"Critica",IF(O12>=12,"Alta",IF(O12>=6,"Media","Baja"))) | Q12: Gerente del Proyecto | R12: RRHH + Arquitectura + Lider Tecnico | S12: Formacion temprana del equipo | T12: Mitigar | U12: Capacitacion intensiva, coaching, acompanamiento externo y revisiones de arquitectura | V12: Curva de aprendizaje mas prolongada de lo esperado | W12: No
A13: R9 | B13: En caso de falla, el retorno al sistema anterior puede no ser viable | C13: Fallo del plan de rollback | D13: Cambios irreversibles, datos ya transformados y rollback no ensayado | E13: 2026-05-09 | F13: Amenaza | G13: Operacional / Continuidad | H13: Continuidad y disponibilidad | I13: Directo | J13: 3 | K13: 4 | L13: 5 | M13: 4 | N13: 5 | O13: =J13*MAX(K13:N13) | P13: =IF(O13>=16,"Critica",IF(O13>=12,"Alta",IF(O13>=6,"Media","Baja"))) | Q13: Lider de Migracion | R13: Infraestructura + DBA + Operaciones | S13: Disenar reversa desde el inicio | T13: Mitigar | U13: Definir criterios de abort, backup consistente, rollback ensayado y scripts reversibles | V13: Recuperacion mas lenta que la prevista | W13: No
A14: R10 | B14: Cambios en procesos y herramientas pueden generar resistencia interna | C14: Resistencia al cambio de usuarios y areas operativas | D14: Comunicacion insuficiente, temor al cambio y poca capacitacion | E14: 2026-05-09 | F14: Amenaza | G14: Organizacional | H14: Adopcion y operacion estable | I14: Indirecto | J14: 3 | K14: 3 | L14: 3 | M14: 2 | N14: 4 | O14: =J14*MAX(K14:N14) | P14: =IF(O14>=16,"Critica",IF(O14>=12,"Alta",IF(O14>=6,"Media","Baja"))) | Q14: Lider de Cambio | R14: RRHH + Operaciones + PM | S14: Plan de cambio organizacional | T14: Mitigar | U14: Comunicacion por fases, capacitaciones, manuales y soporte reforzado durante salida en vivo | V14: Mayor volumen de incidencias de usuario | W14: No
A15: R11 | B15: El uso de servicios cloud puede elevar el gasto operacional | C15: Costos de nube superiores al presupuesto | D15: Sobredimensionamiento, mala optimizacion y consumo no controlado | E15: 2026-05-09 | F15: Amenaza | G15: Financiero | H15: Presupuesto | I15: Indirecto | J15: 3 | K15: 2 | L15: 3 | M15: 5 | N15: 3 | O15: =J15*MAX(K15:N15) | P15: =IF(O15>=16,"Critica",IF(O15>=12,"Alta",IF(O15>=6,"Media","Baja"))) | Q15: Cloud Lead | R15: Finanzas TI + DevOps | S15: Controles de costo desde el inicio | T15: Mitigar | U15: FinOps, etiquetado, alarmas de consumo, rightsizing y revision mensual de gasto | V15: Ajustes presupuestarios adicionales | W15: No
A16: R12 | B16: Dependencia tecnologica fuerte de proveedor cloud y terceros | C16: Lock-in tecnologico o incumplimiento de terceros | D16: Uso excesivo de servicios propietarios y SLAs debiles | E16: 2026-05-09 | F16: Amenaza | G16: Proveedores / Estrategico | H16: Continuidad, costos y flexibilidad | I16: Indirecto | J16: 2 | K16: 3 | L16: 3 | M16: 4 | N16: 3 | O16: =J16*MAX(K16:N16) | P16: =IF(O16>=16,"Critica",IF(O16>=12,"Alta",IF(O16>=6,"Media","Baja"))) | Q16: Gerente de Proveedores | R16: Compras + Arquitectura | S16: Evaluacion contractual y tecnica de proveedores | T16: Mitigar / Transferir | U16: Asegurar SLAs, diseno portable cuando sea posible, multi-zona y plan alternativo | V16: Dependencia parcial inevitable del proveedor principal | W16: No
... A20: R16 | B20: Alta carga operativa durante la salida en vivo y estabilizacion | C20: Sobrecarga operativa post go-live | D20: Volumen alto de incidencias, soporte insuficiente y falta de runbooks | E20: 2026-05-09 | F20: Amenaza | G20: Operacional | H20: Estabilidad del servicio y atencion al cliente | I20: Directo | J20: 4 | K20: 3 | L20: 4 | M20: 3 | N20: 5 | O20: =J20*MAX(K20:N20) | P20: =IF(O20>=16,"Critica",IF(O20>=12,"Alta",IF(O20>=6,"Media","Baja"))) | Q20: Gerente de Operaciones | R20: Mesa de Ayuda + SRE + Soporte Apps | S20: Reforzar operacion de estabilizacion | T20: Mitigar | U20: War room 24/7, escalamiento definido, soporte ampliado, manuales y monitoreo intensivo | V20: Fatiga del equipo y tiempos de respuesta mayores | W20: No

Sheet Resumen
A1: Resumen del Registro de Riesgos
A3: Proyecto | B3: Migracion y modernizacion de un Core Bancario | D3: Metricas
A4: Clientes activos | B4: 500,000 | D4: Total riesgos | E4: =COUNTA('Registro de Riesgos'!A5:A20)
A5: Inactividad maxima | B5: 30 minutos | D5: Critica | E5: =COUNTIF('Registro de Riesgos'!P5:P20,"Critica")
A6: Plazo objetivo | B6: 8 meses | D6: Alta | E6: =COUNTIF('Registro de Riesgos'!P5:P20,"Alta")
A7: Fecha de elaboracion | B7: 2026-05-09 | D7: Media | E7: =COUNTIF('Registro de Riesgos'!P5:P20,"Media")
D8: Baja | E8: =COUNTIF('Registro de Riesgos'!P5:P20,"Baja")
D9: Riesgos activos | E9: =COUNTIF('Registro de Riesgos'!W5:W20,"Si")
A10: Escala de valoracion
A11: Valoracion global = Probabilidad x mayor impacto entre alcance, tiempo, costo y calidad.
A12: Prioridades: Critica >=16, Alta 12-15, Media 6-11, Baja 1-5.
A14: Riesgos mas prioritarios
A15: ID | B15: Riesgo | C15: Prioridad | D15: Valoracion | E15: Dueno | F15: Responsable
A16: R1 | B16: Interrupcion del servicio superior a 30 minutos durante el cutover | C16: Critica | D16: 20 | E16: Lider de Migracion | F16: Operaciones + Infraestructura
A17: R4 | B17: Bajo desempeno del nuevo core en produccion | C17: Critica | D17: 20 | E17: Arquitecto de Solucion | F17: SRE / DevOps / Arquitectura
A18: R5 | B18: Fallas en integraciones con sistemas internos y externos | C18: Critica | D18: 20 | E18: Lider de Integraciones | F18: Equipos de Canales / Middleware
A19: R7 | B19: Retraso del cronograma por complejidad no prevista | C19: Critica | D19: 20 | E19: Project Manager | F19: PMO + Arquitectura + Lideres Tecnicos
A20: R13 | B20: Ambientes de prueba no representativos | C20: Critica | D20: 20 | E20: QA Lead | F20: QA + Infraestructura + Arquitectura
